deployer/__init__.py
deployer/deployer.py
deployer/globals.py
deployer/nat_utils.py
deployer/network.py
deployer/topology.py
deployer/utils.py
deployer/virtual_machine.py
deployer/tests/__init__.py
deployer/tests/test_deployer.py
deployer/tests/test_network.py
deployer/tests/test_virtual_machines.py
topology_deployer-0.2.2.dist-info/LICENSE
topology_deployer-0.2.2.dist-info/METADATA
topology_deployer-0.2.2.dist-info/WHEEL
topology_deployer-0.2.2.dist-info/entry_points.txt
topology_deployer-0.2.2.dist-info/top_level.txt
topology_deployer-0.2.2.dist-info/RECORD
