Metadata-Version: 2.1
Name: topology-deployer
Version: 0.2.2
Summary: A python tool to deploy topology defined in a json config
Home-page: https://github.com/vpatel95/libvirt-topology
Author: Ved Patel
Project-URL: Bug Tracker, https://github.com/vpatel95/libvirt-topology/issues
Classifier: Programming Language :: Python :: 3
Classifier: License :: OSI Approved :: MIT License
Classifier: Operating System :: POSIX :: Linux
Requires-Python: >=3.6
License-File: LICENSE
Requires-Dist: pyyaml
Requires-Dist: ipaddress
Requires-Dist: psutil
Requires-Dist: pytest
